sbom4rust/__init__.py
sbom4rust/cli.py
sbom4rust/scanner.py
sbom4rust/version.py
sbom4rust-0.6.0.dist-info/LICENSE
sbom4rust-0.6.0.dist-info/METADATA
sbom4rust-0.6.0.dist-info/WHEEL
sbom4rust-0.6.0.dist-info/entry_points.txt
sbom4rust-0.6.0.dist-info/top_level.txt
sbom4rust-0.6.0.dist-info/RECORD
